nonebot_plugin_rikka_extra-0.2.0.dist-info/WHEEL
nonebot_plugin_rikka_extra-0.2.0.dist-info/top_level.txt
nonebot_plugin_rikka_extra-0.2.0.dist-info/METADATA
nonebot_plugin_rikka_extra-0.2.0.dist-info/RECORD
nonebot_plugin_rikka_extra/score.py
nonebot_plugin_rikka_extra/server_status.py
nonebot_plugin_rikka_extra/server_status.cpython-39-i386-linux-gnu.so
nonebot_plugin_rikka_extra/score.cpython-39-i386-linux-gnu.so
nonebot_plugin_rikka_extra/__init__.py
nonebot_plugin_rikka_extra/sdgb/payload.cpython-39-i386-linux-gnu.so
nonebot_plugin_rikka_extra/sdgb/sdgb.cpython-39-i386-linux-gnu.so
nonebot_plugin_rikka_extra/sdgb/payload.py
nonebot_plugin_rikka_extra/sdgb/allnet.py
nonebot_plugin_rikka_extra/sdgb/chime.py
nonebot_plugin_rikka_extra/sdgb/configs.cpython-39-i386-linux-gnu.so
nonebot_plugin_rikka_extra/sdgb/configs.py
nonebot_plugin_rikka_extra/sdgb/chime.cpython-39-i386-linux-gnu.so
nonebot_plugin_rikka_extra/sdgb/allnet.cpython-39-i386-linux-gnu.so
nonebot_plugin_rikka_extra/sdgb/encrypt.py
nonebot_plugin_rikka_extra/sdgb/__init__.py
nonebot_plugin_rikka_extra/sdgb/encrypt.cpython-39-i386-linux-gnu.so
nonebot_plugin_rikka_extra/sdgb/sdgb.py
