Metadata-Version: 2.4
Name: nonebot-plugin-rikka-extra
Version: 0.2.0
Summary: nonebot-plugin-rikka-extra
Requires-Python: <4.0,>=3.9
Requires-Dist: aiohttp>=3.9.0
Requires-Dist: httpx>=0.27.0
Requires-Dist: pytz>=2025.2
Requires-Dist: pycryptodome>=3.23.0
